[
  [
    {
      "branch": [
        10
      ]
    },
    {
      "branch": [
        24
      ]
    },
    {
      "branch": [
        4
      ]
    },
    {
      "gen": [
        2
      ]
    },
    {
      "branch": [
        7
      ]
    },
    {
      "gen": [
        6
      ]
    },
    {
      "branch": [
        19
      ]
    },
    {
      "branch": [
        8
      ]
    },
    {
      "branch": [
        38
      ]
    },
    {
      "branch": [
        25
      ]
    },
    {
      "branch": [
        40
      ]
    },
    {
      "branch": [
        21
      ]
    },
    {
      "branch": [
        39
      ]
    },
    {
      "branch": [
        29
      ]
    },
    {
      "branch": [
        17
      ]
    },
    {
      "gen": [
        3
      ]
    },
    {
      "gen": [
        4
      ]
    },
    {
      "branch": [
        37
      ]
    },
    {
      "branch": [
        15
      ]
    },
    {
      "branch": [
        30
      ]
    },
    {
      "branch": [
        6
      ]
    },
    {
      "branch": [
        22
      ]
    },
    {
      "branch": [
        33
      ]
    },
    {
      "branch": [
        20
      ]
    },
    {
      "branch": [
        35
      ]
    },
    {
      "branch": [
        32
      ]
    },
    {
      "branch": [
        2
      ]
    },
    {
      "branch": [
        31
      ]
    },
    {
      "branch": [
        12
      ]
    },
    {
      "branch": [
        14
      ]
    },
    {
      "branch": [
        23
      ]
    },
    {
      "branch": [
        9
      ]
    },
    {
      "branch": [
        11
      ]
    },
    {
      "branch": [
        41
      ]
    },
    {
      "branch": [
        5
      ]
    },
    {
      "gen": [
        5
      ]
    },
    {
      "branch": [
        28
      ]
    },
    {
      "branch": [
        3
      ]
    },
    {
      "branch": [
        18
      ]
    },
    {
      "branch": [
        27
      ]
    },
    {
      "branch": [
        26
      ]
    },
    {
      "branch": [
        1
      ]
    }
  ]
]
